RPi/__init__.py
RPi/core.py
RPi/GPIO/__init__.py
RPi/GPIO_DEVEL/__init__.py
examples/__init__.py
examples/button_test.py
examples/callback.py
examples/callback2.py
examples/event_test.py
examples/flash18.py
examples/input_examples.py
examples/morse.py
examples/output_examples.py
examples/pwm1.py
examples/pwm2.py
examples/pwm3.py
examples/pwm4.py
examples/pwm_usage.py
examples/random_usage.py
examples/try_import.py
tests/__init__.py
tests/test_gpio.py
tests/test_pwm.py
RPi.GPIO2-0.3.0a2.dist-info/LICENSE.txt
RPi.GPIO2-0.3.0a2.dist-info/METADATA
RPi.GPIO2-0.3.0a2.dist-info/WHEEL
RPi.GPIO2-0.3.0a2.dist-info/top_level.txt
RPi.GPIO2-0.3.0a2.dist-info/RECORD
