Metadata-Version: 2.1
Name: RPi.GPIO2
Version: 0.3.0a2
Summary: Compatibility layer between RPi.GPIO syntax and libgpiod semantics
Home-page: https://github.com/underground-software/python3-libgpiod-rpi
Author: Joel Savitz
Author-email: joelsavitz@gmail.com
License: UNKNOWN
Project-URL: Source, https://github.com/underground-software/python3-libgpiod-rpi
Project-URL: Bug Reports, https://github.com/underground-software/python3-libgpiod-rpi/issues
Keywords: Raspberry Pi GPIO libgpiod RPi.GPIO
Platform: UNKNOWN
Classifier: Development Status :: 3 - Alpha
Classifier: License :: OSI Approved :: GNU General Public License v3 or later (GPLv3+)
Classifier: Operating System :: POSIX :: Linux
Classifier: Intended Audience :: Education
Classifier: Intended Audience :: Developers
Classifier: Programming Language :: Python :: 3 :: Only
Classifier: Programming Language :: Python :: 3
Classifier: Programming Language :: Python :: 3.7
Classifier: Topic :: Home Automation
Classifier: Topic :: Software Development
Classifier: Topic :: Software Development :: Libraries
Classifier: Topic :: Software Development :: Libraries :: Application Frameworks
Classifier: Topic :: System :: Hardware
Requires-Python: >=3.7
